{"modes": [{"name": "Ionian (Major)", "pattern": "Tone - Tone - Semitone - Tone - Tone - Tone - Semitone", "sonority": "Bright, stable, cheerful.", "example": ["C", "D", "E", "F", "G", "A", "B", "C"]}, {"name": "Dorian", "pattern": "Tone - Semitone - Tone - Tone - Tone - Semitone - Tone", "sonority": "Solemn, ancient, between major and minor.", "example": ["D", "E", "F", "G", "A", "B", "C", "D"]}, {"name": "Phrygian", "pattern": "Semitone - Tone - Tone - Tone - Semitone - Tone - Tone", "sonority": "Exotic, mysterious, often associated with flamenco.", "example": ["E", "F", "G", "A", "B", "C", "D", "E"]}, {"name": "Lydian", "pattern": "Tone - Tone - Tone - Semitone - Tone - Tone - Semitone", "sonority": "Bright, dreamy, cheerful (with an augmented fourth).", "example": ["F", "G", "A", "B", "C", "D", "E", "F"]}, {"name": "Mixolydian", "pattern": "Tone - Tone - Semitone - Tone - Tone - Semitone - Tone", "sonority": "Cheerful, but with a relaxed or folk character (flattened seventh).", "example": ["G", "A", "B", "C", "D", "E", "F", "G"]}, {"name": "Aeolian (Natural Minor)", "pattern": "Tone - Semitone - Tone - Tone - Semitone - Tone - Tone", "sonority": "Melancholic, sad.", "example": ["A", "B", "C", "D", "E", "F", "G", "A"]}, {"name": "Locrian", "pattern": "Semitone - Tone - Tone - Semitone - Tone - Tone - Tone", "sonority": "Dark, unstable, tense (due to the diminished fifth).", "example": ["B", "C", "D", "E", "F", "G", "A", "B"]}], "mode_relations": {"major_modes": ["Ionian", "Lydian", "Mixolydian"], "minor_modes": ["Aeolian", "Dorian", "Phrygian", "Locrian"]}}